tochka_api/__init__.py
tochka_api/settings.py
tochka_api/token_manager.py
tochka_api/exceptions/__init__.py
tochka_api/exceptions/base.py
tochka_api/models/__init__.py
tochka_api/models/permissions.py
tochka_api/models/tokens.py
tochka_api/models/responses/__init__.py
tochka_api/models/responses/accounts.py
tochka_api/models/responses/balances.py
tochka_api/models/responses/base.py
tochka_api/models/responses/consents.py
tochka_api/models/responses/sbp_accounts.py
tochka_api/models/responses/sbp_legal.py
tochka_api/models/responses/sbp_merchants.py
tochka_api/models/responses/sbp_qr.py
tochka_api/models/responses/sbp_refunds.py
tochka_api-0.1.0.dist-info/LICENSE
tochka_api-0.1.0.dist-info/METADATA
tochka_api-0.1.0.dist-info/WHEEL
tochka_api-0.1.0.dist-info/top_level.txt
tochka_api-0.1.0.dist-info/RECORD
