Metadata-Version: 2.1
Name: tochka-api
Version: 0.1.0
Summary: Simple Tochka Bank Open API client
Home-page: https://github.com/WhiteApfel/tochka_api
Author: WhiteApfel
Author-email: white@pfel.ru
License: Mozilla Public License 2.0
Project-URL: Source code, https://github.com/WhiteApfel/tochka-api
Project-URL: Write me, https://t.me/whiteapfel
Keywords: tochka openapi api bank
License-File: LICENSE
Requires-Dist: pydantic (~=1.10.1)
Requires-Dist: httpx (~=0.23.0)
Requires-Dist: ujson (~=5.4.0)
Requires-Dist: appdirs (~=1.4.4)
